Metadata-Version: 2.1
Name: nb-robot
Version: 1.0.0
Summary: Robot Framework Integration Plugin
Home-page: 
Author: Renato Almeida de Oliveira Zaroubin
Author-email: renato.almeida.oliveira@gmail.com
Classifier: Development Status :: 2 - Pre-Alpha
Classifier: Framework :: Django
Classifier: Programming Language :: Python :: 3
License-File: LICENSE
Requires-Dist: robotframework
